AUTHORS
Changelog
LICENSE
MANIFEST.in
README
README.rst
setup.cfg
setup.py
cell/__init__.py
cell/actors.py
cell/agents.py
cell/exceptions.py
cell/models.py
cell/presence.py
cell/results.py
cell.egg-info/PKG-INFO
cell.egg-info/SOURCES.txt
cell.egg-info/dependency_links.txt
cell.egg-info/entry_points.txt
cell.egg-info/not-zip-safe
cell.egg-info/requires.txt
cell.egg-info/top_level.txt
cell/bin/__init__.py
cell/bin/base.py
cell/bin/cell.py
cell/g/__init__.py
cell/g/eventlet.py
cell/utils/__init__.py
examples/clex.py
examples/distributed_cache.py
examples/hello.py
requirements/default.txt
requirements/pkgutils.txt
requirements/test.txt